pychor/__init__.py
pychor/choreography.py
pychor/object_stream.py
pychor/tcp_backend.py
pychor-0.2.2.dist-info/licenses/LICENSE
pychor-0.2.2.dist-info/METADATA
pychor-0.2.2.dist-info/WHEEL
pychor-0.2.2.dist-info/top_level.txt
pychor-0.2.2.dist-info/RECORD
