Metadata-Version: 2.4
Name: pychor
Version: 0.2.2
Summary: Library-based choreographic programming for Python
Author-email: Joseph Near <jnear@uvm.edu>
License-Expression: MIT
Project-URL: Repository, https://github.com/uvm-plaid/pychor
Requires-Python: >=3.9
License-File: LICENSE
Provides-Extra: examples
Requires-Dist: galois; extra == "examples"
Requires-Dist: pynacl; extra == "examples"
Requires-Dist: numpy; extra == "examples"
Dynamic: license-file
